wsgi_basic_auth.py
wsgi_basic_auth_isl-1.0.4.dist-info/DESCRIPTION.rst
wsgi_basic_auth_isl-1.0.4.dist-info/METADATA
wsgi_basic_auth_isl-1.0.4.dist-info/RECORD
wsgi_basic_auth_isl-1.0.4.dist-info/WHEEL
wsgi_basic_auth_isl-1.0.4.dist-info/metadata.json
wsgi_basic_auth_isl-1.0.4.dist-info/top_level.txt
